aioradio/__init__.py
aioradio/ds_utils.py
aioradio/file_ingestion.py
aioradio/jira.py
aioradio/logger.py
aioradio/long_running_jobs.py
aioradio/psycopg2.py
aioradio/pyodbc.py
aioradio/redis.py
aioradio/utils.py
aioradio/aws/dynamodb.py
aioradio/aws/moto_server.py
aioradio/aws/s3.py
aioradio/aws/secrets.py
aioradio/aws/sqs.py
aioradio/aws/utils.py
aioradio-0.21.10.dist-info/LICENSE
aioradio-0.21.10.dist-info/METADATA
aioradio-0.21.10.dist-info/WHEEL
aioradio-0.21.10.dist-info/top_level.txt
aioradio-0.21.10.dist-info/RECORD
