Metadata-Version: 2.2
Name: aioradio
Version: 0.21.10
Summary: Generic asynchronous i/o python utilities for AWS services (SQS, S3, DynamoDB, Secrets Manager), Redis, MSSQL (pyodbc), JIRA and more
Home-page: https://github.com/nrccua/aioradio
Author: Encoura DS Team
Author-email: tim.reichard@encoura.org
License: MIT
Classifier: Programming Language :: Python :: 3
Classifier: Operating System :: OS Independent
Requires-Python: >=3.10
License-File: LICENSE
Requires-Dist: cython>=0.29.33
Requires-Dist: aioboto3==14.1.0
Requires-Dist: aiojobs>=1.0.0
Requires-Dist: backoff>=2.1.2
Requires-Dist: botocore==1.37.1
Requires-Dist: boto3==1.37.1
Requires-Dist: ddtrace>=0.60.1
Requires-Dist: faust-cchardet>=2.1.18
Requires-Dist: fakeredis>=2.20.0
Requires-Dist: httpx>=0.23.0
Requires-Dist: mandrill>=1.0.60
Requires-Dist: mlflow>=2.10.2
Requires-Dist: numpy>=1.26.4
Requires-Dist: openpyxl==3.0.10
Requires-Dist: orjson>=3.6.8
Requires-Dist: pandas>=1.3.5
Requires-Dist: polars>=0.19.12
Requires-Dist: pyarrow>=13.0.0
Requires-Dist: pysmb>=1.2.7
Requires-Dist: python-json-logger>=2.0.2
Requires-Dist: redis>=5.0.1
Dynamic: author
Dynamic: author-email
Dynamic: classifier
Dynamic: description
Dynamic: description-content-type
Dynamic: home-page
Dynamic: license
Dynamic: requires-dist
Dynamic: requires-python
Dynamic: summary
